[
  {
    "title": "Phyto-Nanomedicine",
    "content": "Author(s): Hitesh Chopra. First published: 2025. Languages: eng. Editions: 2. Subjects: Not specified.",
    "timestamp": "2026-03-15T23:49:45.257025+00:00",
    "source": "open_library",
    "confidence": 0.93
  },
  {
    "title": "Out-Brake",
    "content": "Author(s): Zsm. First published: 2025. Languages: eng. Editions: 3. Subjects: Not specified.",
    "timestamp": "2026-03-15T23:49:45.257025+00:00",
    "source": "open_library",
    "confidence": 0.93
  },
  {
    "title": "Next Decade of Discovery in Solar and Space Physics",
    "content": "Author(s): National Academies of Sciences, Engineering, and Medicine, Division on Engineering and Physical Sciences, Space Studies Board, Committee on a Decadal Survey for Solar and Space Physics (Heliophysics) 2024-2033. First published: 2025. Languages: eng. Editions: 1. Subjects: Not specified.",
    "timestamp": "2026-03-15T23:49:45.257025+00:00",
    "source": "open_library",
    "confidence": 0.93
  },
  {
    "title": "Revolutionizing Drug Discovery",
    "content": "Author(s): Swati Verma, Ajmer Singh Grewal, Neelam Singh, Hemlata Nimesh. First published: 2025. Languages: eng. Editions: 1. Subjects: Not specified.",
    "timestamp": "2026-03-15T23:49:45.257025+00:00",
    "source": "open_library",
    "confidence": 0.93
  },
  {
    "title": "Discovery Science",
    "content": "Author(s): Dino Pedreschi, Anna Monreale, Riccardo Guidotti, Roberto Pellungrini, Francesca Naretto. First published: 2025. Languages: eng. Editions: 2. Subjects: Not specified.",
    "timestamp": "2026-03-15T23:49:45.257025+00:00",
    "source": "open_library",
    "confidence": 0.93
  },
  {
    "title": "Take to the Trees",
    "content": "Author(s): Marguerite Holloway. First published: 2025. Languages: eng. Editions: 2. Subjects: Not specified.",
    "timestamp": "2026-03-15T23:49:45.257025+00:00",
    "source": "open_library",
    "confidence": 0.93
  },
  {
    "title": "Science Year by Year",
    "content": "Author(s): DK Publishing. First published: 2025. Languages: eng. Editions: 1. Subjects: Not specified.",
    "timestamp": "2026-03-15T23:49:45.257025+00:00",
    "source": "open_library",
    "confidence": 0.93
  },
  {
    "title": "Renaissance in GPCR Research and Drug Discovery",
    "content": "Author(s): Terry P. Kenakin. First published: 2025. Languages: eng. Editions: 1. Subjects: Not specified.",
    "timestamp": "2026-03-15T23:49:45.257025+00:00",
    "source": "open_library",
    "confidence": 0.93
  },
  {
    "title": "Seeds of Discovery",
    "content": "Author(s): Lori Alexander, Rebecca Santo. First published: 2025. Languages: eng. Editions: 1. Subjects: Not specified.",
    "timestamp": "2026-03-15T23:49:45.257025+00:00",
    "source": "open_library",
    "confidence": 0.93
  },
  {
    "title": "Salmon Cannon and the Levitating Frog",
    "content": "Author(s): Carly Anne York. First published: 2025. Languages: eng. Editions: 2. Subjects: Not specified.",
    "timestamp": "2026-03-15T23:49:45.257025+00:00",
    "source": "open_library",
    "confidence": 0.93
  }
]